odoo/addons/stock_picking_warn_message/README.rst
odoo/addons/stock_picking_warn_message/__init__.py
odoo/addons/stock_picking_warn_message/__manifest__.py
odoo/addons/stock_picking_warn_message/i18n/stock_picking_warn_message.pot
odoo/addons/stock_picking_warn_message/models/__init__.py
odoo/addons/stock_picking_warn_message/models/stock_picking.py
odoo/addons/stock_picking_warn_message/readme/CONTRIBUTORS.rst
odoo/addons/stock_picking_warn_message/readme/DESCRIPTION.rst
odoo/addons/stock_picking_warn_message/static/description/icon.png
odoo/addons/stock_picking_warn_message/static/description/index.html
odoo/addons/stock_picking_warn_message/tests/__init__.py
odoo/addons/stock_picking_warn_message/tests/test_stock_picking_warn_message.py
odoo/addons/stock_picking_warn_message/views/stock_picking_views.xml
odoo13_addon_stock_picking_warn_message-13.0.1.0.2.dist-info/METADATA
odoo13_addon_stock_picking_warn_message-13.0.1.0.2.dist-info/WHEEL
odoo13_addon_stock_picking_warn_message-13.0.1.0.2.dist-info/top_level.txt
odoo13_addon_stock_picking_warn_message-13.0.1.0.2.dist-info/RECORD
